yzc/__init__.py
yzc/cli.py
yzc-0.2.3.dist-info/METADATA
yzc-0.2.3.dist-info/WHEEL
yzc-0.2.3.dist-info/entry_points.txt
yzc-0.2.3.dist-info/top_level.txt
yzc-0.2.3.dist-info/RECORD
